actual/__init__.py
actual/budgets.py
actual/crypto.py
actual/database.py
actual/exceptions.py
actual/migrations.py
actual/protobuf_models.py
actual/queries.py
actual/rules.py
actual/schedules.py
actual/version.py
actual/api/__init__.py
actual/api/bank_sync.py
actual/api/models.py
actual/cli/__init__.py
actual/cli/config.py
actual/cli/formatters.py
actual/cli/main.py
actual/utils/__init__.py
actual/utils/changeset.py
actual/utils/conversions.py
actual/utils/openid.py
actual/utils/storage.py
actual/utils/title.py
actualpy-0.20.0.dist-info/licenses/LICENSE
actualpy-0.20.0.dist-info/METADATA
actualpy-0.20.0.dist-info/WHEEL
actualpy-0.20.0.dist-info/entry_points.txt
actualpy-0.20.0.dist-info/top_level.txt
actualpy-0.20.0.dist-info/RECORD
