Metadata-Version: 2.4
Name: actualpy
Version: 0.20.0
Summary: Implementation of the Actual API to interact with Actual over Python.
Author-email: Brunno Vanelli <brunnovanelli@gmail.com>
Project-URL: Homepage, https://github.com/bvanelli/actualpy
Project-URL: Documentation, https://actualpy.readthedocs.io/
Project-URL: Repository, https://github.com/bvanelli/actualpy.git
Project-URL: Bug Tracker, https://github.com/bvanelli/actualpy/issues
Keywords: actual,actualbudget,api,client
Classifier: Programming Language :: Python
Classifier: Programming Language :: Python :: 3
Classifier: Programming Language :: Python :: 3.10
Classifier: Programming Language :: Python :: 3.11
Classifier: Programming Language :: Python :: 3.12
Classifier: Programming Language :: Python :: 3.13
Classifier: Programming Language :: Python :: 3.14
Requires-Python: >=3.10.0
License-File: LICENSE
Requires-Dist: requests>=2
Requires-Dist: sqlmodel>=0.0.18
Requires-Dist: pydantic<3,>=2
Requires-Dist: sqlalchemy>=2
Requires-Dist: proto-plus>=1
Requires-Dist: protobuf>=4
Requires-Dist: cryptography>=42
Requires-Dist: python-dateutil>=2.9.0
Provides-Extra: cli
Requires-Dist: rich>=13; extra == "cli"
Requires-Dist: typer>=0.12.0; extra == "cli"
Requires-Dist: pyyaml>=6; extra == "cli"
Dynamic: license-file
